dtbdump.py
fdtmerge.py
jsonfdtdump.py
setup.py
pyfdt/__init__.py
pyfdt/pyfdt.py
pyfdt.egg-info/PKG-INFO
pyfdt.egg-info/SOURCES.txt
pyfdt.egg-info/dependency_links.txt
pyfdt.egg-info/top_level.txt