Metadata-Version: 1.0
Name: pyfdt
Version: 0.3
Summary: Python Flattened Device Tree Library
Home-page: https://github.com/superna9999/pyfdt
Author: Neil 'Superna' Armstrong
Author-email: superna9999@gmail.com
License: UNKNOWN
Platform: UNKNOWN
